phantasm/__init__.py
phantasm-0.2.data/scripts/phantasm_data_comparison.py
phantasm-0.2.data/scripts/phantasm_data_rescale.py
phantasm-0.2.data/scripts/phantasm_generate_cids.py
phantasm-0.2.data/scripts/phantasm_data_binning.py
phantasm-0.2.data/scripts/phantasm_compare.py
phantasm-0.2.data/scripts/phantasm_data_transformation.py
phantasm-0.2.data/scripts/phantasm_cluster.R
phantasm-0.2.dist-info/top_level.txt
phantasm-0.2.dist-info/METADATA
phantasm-0.2.dist-info/DESCRIPTION.rst
phantasm-0.2.dist-info/metadata.json
phantasm-0.2.dist-info/WHEEL
phantasm-0.2.dist-info/RECORD
