Metadata-Version: 2.0
Name: phantasm
Version: 0.2
Summary: Python tools for dynamic clustering
Home-page: UNKNOWN
Author: Eric Rasche
Author-email: esr@tamu.edu
License: UNKNOWN
Platform: UNKNOWN
Classifier: Development Status :: 3 - Alpha
Classifier: Operating System :: OS Independent
Classifier: Intended Audience :: Science/Research
Classifier: Environment :: Console
Classifier: License :: OSI Approved :: Apache Software License
Requires-Dist: python-levenshtein
Requires-Dist: numpy
Requires-Dist: scikit-learn
Requires-Dist: biopython
